{
  "title": "Visualize This! Creating Stunning Graphs with Napkin AI",
  "slug": "visualize-this-creating-stunning-graphs-with-napkin-ai",
  "youtubeId": "2lAQCiMTr68",
  "format": "video",
  "duration": "6:07",
  "published": "2025-04-03",
  "category": "content",
  "description": "Step-by-step walkthrough of Napkin AI: turn plain text into clean graphs and visuals in seconds, no design software needed.",
  "tags": [
    "napkin app review",
    "ai tools",
    "napkin ai tutorial",
    "ai graphic design",
    "ai-generated visuals",
    "text to visuals",
    "how to use napkin ai",
    "ai tools for content creators"
  ],
  "verified": [
    "title",
    "youtubeId",
    "format",
    "duration",
    "published"
  ],
  "generated": [
    "slug",
    "category",
    "description",
    "tags"
  ]
}