{
  "title": "Creating Realistic AI Avatars Is Now Extremely Easy",
  "slug": "creating-realistic-ai-avatars-is-now-extremely-easy",
  "youtubeId": "IgIlPCuvg_4",
  "format": "video",
  "duration": "2:36",
  "published": "2025-03-25",
  "category": "ai-tools",
  "description": "Walkthrough of Virbo AI: spin up realistic talking avatars for faceless videos, no camera needed. Features, use cases, and a step-by-step demo.",
  "tags": [
    "virbo ai",
    "ai avatar tool",
    "faceless video creation",
    "ai video generator",
    "text to video ai",
    "ai-powered content creation",
    "ai video creator",
    "image to video"
  ],
  "verified": [
    "title",
    "youtubeId",
    "format",
    "duration",
    "published"
  ],
  "generated": [
    "slug",
    "category",
    "description",
    "tags"
  ]
}