{
  "title": "Create AMAZING Talking Photos With Hedra AI Easily",
  "slug": "create-amazing-talking-photos-with-hedra-ai-easily",
  "youtubeId": "rAzcX5LOu9c",
  "format": "short",
  "duration": "0:44",
  "published": "2025-03-11",
  "category": "video-creation",
  "description": "Turn any photo into a realistic talking avatar with Hedra AI. Upload an image, add a voice, export a lip-synced video in seconds.",
  "tags": [
    "hedra ai",
    "ai character creation",
    "ai art generator",
    "ai talking avatar",
    "ai avatar generator",
    "image to video",
    "text to video",
    "ai video generation"
  ],
  "verified": [
    "title",
    "youtubeId",
    "format",
    "duration",
    "published"
  ],
  "generated": [
    "slug",
    "category",
    "description",
    "tags"
  ]
}