{
  "title": "Best AI Website Builders of 2024 No Coding Required  | Framer, CodeDesign, and 10Web Showdown",
  "slug": "best-ai-website-builders-of-2024-no-coding-required-framer-codedesign-and-10web-showdown",
  "youtubeId": "xX4JjX_nvWw",
  "format": "video",
  "duration": "4:16",
  "published": "2024-10-04",
  "category": "ai-tools",
  "description": "Head-to-head showdown of Framer, CodeDesign, and 10Web — the top no-code AI website builders of 2024.",
  "tags": [
    "ai website builder",
    "framer website builder",
    "codedesign ai",
    "10web ai wordpress",
    "best no-code website builder",
    "ai tools for web design",
    "automated web development",
    "website builder comparison"
  ],
  "verified": [
    "title",
    "youtubeId",
    "format",
    "duration",
    "published"
  ],
  "generated": [
    "slug",
    "category",
    "description",
    "tags"
  ]
}